{
    "id": "123680258",
    "name": "Tsunami",
    "author": "OniLink",
    "creators": ["OniLink"],
    "verifier": "Zoink",
    "isVerified": false,
    "verification": "",
    "showcase": "https://youtu.be/7NqR0NxxNt4?si=yv7BRdcvh-J1eXn_",
    "lastUpd": "18.06.2026",

    "percentToQualify": 1,
    "records": [
        {
            "user": "none",
            "link": "",
            "percent": 0,
            "hz": 0
        }
    ],
    "run": [
        {
            "user": "none",
            "link": "",
            "percent": "0",
            "hz": 0
        }
    ],

    "length": 212,
    "rating": 1,
    "percentFinished": 90,
    "isMain": true,
    "isFuture": false,

    "tags": ["XXL"]
}
