{
    "id": "private",
    "name": "WRATH",
    "author": "CherryTeam",
    "creators": [],
    "verifier": "SerVax",
    "isVerified": false,
    "verification": "",
    "showcase": "https://youtu.be/-jvx1MJTP-Q?si=ndDdmg6b5FerUwQH",
    "percentToQualify": 1,
    "records": [
        {
            "user": "none",
            "link": "",
            "percent": 0,
            "hz": 0
        }
    ],
    "run": [
        {
            "user": "none",
            "link": "",
            "percent": "0",
            "hz": 0
        }
    ],
    "length": 155,
    "rating": 1,
    "percentFinished": 100,

    "isMain": true,
    "isFuture": true,
    "tags": ["XL", "Quality", "Finished"],
    "lastUpd": "12.12.2025"
}
